README.rst
setup.cfg
setup.py
graytail/__init__.py
graytail/graytail.py
graytail.egg-info/PKG-INFO
graytail.egg-info/SOURCES.txt
graytail.egg-info/dependency_links.txt
graytail.egg-info/entry_points.txt
graytail.egg-info/requires.txt
graytail.egg-info/top_level.txt